get_buildings/__init__.py
get_buildings/main.py
get_buildings-0.1.4.dist-info/METADATA
get_buildings-0.1.4.dist-info/WHEEL
get_buildings-0.1.4.dist-info/entry_points.txt
get_buildings-0.1.4.dist-info/top_level.txt
get_buildings-0.1.4.dist-info/RECORD
