Metadata-Version: 2.1
Name: get-buildings
Version: 0.1.4
Summary: A tool for downloading and processing building footprints using bounding box data.
Home-page: https://github.com/arazshah/get_buildings
Author: Araz Shah
Author-email: araz.shah@gmail.com
License: UNKNOWN
Platform: UNKNOWN
Classifier: Programming Language :: Python :: 3
Classifier: License :: OSI Approved :: MIT License
Classifier: Operating System :: OS Independent
Requires-Python: >=3.6
Requires-Dist: geopandas
Requires-Dist: mercantile
Requires-Dist: pandas
Requires-Dist: shapely
Requires-Dist: tqdm
